module_inject/__init__.py
module_inject/module.py
module_inject-0.0.1.dist-info/METADATA
module_inject-0.0.1.dist-info/WHEEL
module_inject-0.0.1.dist-info/top_level.txt
module_inject-0.0.1.dist-info/RECORD
