Metadata-Version: 2.4
Name: module-inject
Version: 0.0.1
Summary: Module value injection
Requires-Python: >=3.10
